astra/__init__.py
astra/algorithm.py
astra/algorithm_c.cpython-313-x86_64-linux-gnu.so
astra/astra.py
astra/astra_c.cpython-313-x86_64-linux-gnu.so
astra/creators.py
astra/data2d.py
astra/data2d_c.cpython-313-x86_64-linux-gnu.so
astra/data3d.py
astra/data3d_c.cpython-313-x86_64-linux-gnu.so
astra/experimental.cpython-313-x86_64-linux-gnu.so
astra/extrautils.cpython-313-x86_64-linux-gnu.so
astra/functions.py
astra/libastra.so.0
astra/log.py
astra/log_c.cpython-313-x86_64-linux-gnu.so
astra/matlab.py
astra/matrix.py
astra/matrix_c.cpython-313-x86_64-linux-gnu.so
astra/optomo.py
astra/plugin.py
astra/plugin_c.cpython-313-x86_64-linux-gnu.so
astra/projector.py
astra/projector3d.py
astra/projector3d_c.cpython-313-x86_64-linux-gnu.so
astra/projector_c.cpython-313-x86_64-linux-gnu.so
astra/pythonutils.py
astra/tests.py
astra/utils.cpython-313-x86_64-linux-gnu.so
astra/plugins/__init__.py
astra/plugins/cgls.py
astra/plugins/sirt.py
astra_toolbox-2.4.1.dist-info/METADATA
astra_toolbox-2.4.1.dist-info/WHEEL
astra_toolbox-2.4.1.dist-info/top_level.txt
astra_toolbox-2.4.1.dist-info/RECORD
