Metadata-Version: 2.4
Name: astra-toolbox
Version: 2.4.1
Summary: High-performance GPU primitives and algorithms for 2D and 3D tomography
License: GPLv3
Project-URL: Home page, https://astra-toolbox.com
Project-URL: Source, https://github.com/astra-toolbox/astra-toolbox
Requires-Dist: numpy
Requires-Dist: scipy
Requires-Dist: nvidia-cuda-runtime-cu12
Requires-Dist: nvidia-cufft-cu12
Dynamic: description
Dynamic: description-content-type
Dynamic: license
Dynamic: project-url
Dynamic: requires-dist
Dynamic: summary
